{
  "components": {
    "1557111804637_1": {
      "type": "Radio",
      "dataName": "mk_bgDis",
      "label": {
        "description": {
          "icon": "",
          "desc": ""
        },
        "title": "模块背景图片设置"
      },
      "wrapperStyle": {},
      "style": {
        "width": "auto",
        "height": "auto"
      },
      "invisible": false,
      "extension": {
        "confirm": {},
        "shape": "",
        "size": "large",
        "defaultValue": "2",
        "type": "",
        "dataSource": [
          {
            "label": "显示",
            "value": "1"
          },
          {
            "label": "不显示",
            "value": "2"
          }
        ]
      },
      "validateProps": {
        "dataType": "Number",
        "required": false,
        "validate": false
      }
    },
    "1557111804637_2": {
      "type": "SingleImage",
      "dataName": "mk_bgImg",
      "label": {
        "description": {
          "icon": "picture",
          "desc": "背景图片：宽1920内，高不限"
        },
        "title": ""
      },
      "wrapperStyle": {},
      "style": {
        "width": "auto",
        "height": "auto"
      },
      "invisible": false,
      "extension": {
        "size": 2,
        "saveImageSize": false,
        "api": {
          "uploadUrl": "/v1/image_upload.do"
        },
        "lang": {
          "cropUploadLocale": {
            "image": {
              "cancel": "取消",
              "addPhoto": "上传照片"
            },
            "file": {
              "addPhoto": "上传照片"
            },
            "drag": {
              "dropTips": "可以放手了",
              "dragTips": "直接拖动文件到虚线框内即可上传"
            },
            "crop": {
              "save": "保存并关闭",
              "reset": "重新选择",
              "title": "上传"
            }
          },
          "acceptErrMsg": "不支持该类型的图片，请重新选择",
          "cropSmallError": "您上传的图片超过大小限制，请重新选择图片",
          "cropRecommend": "您上传的图片高度或者宽度太小，请选择尺寸足够的图片",
          "uploadErrMsg": "图片上传失败，请重试"
        }
      },
      "validateProps": {
        "dataType": "",
        "required": false,
        "validate": false
      }
    },
    "1557111804637_4": {
      "type": "Radio",
      "dataName": "mk_bgXg",
      "label": {
        "description": {
          "icon": "",
          "desc": "背景图片效果"
        },
        "title": ""
      },
      "wrapperStyle": {},
      "style": {
        "width": "auto",
        "height": "auto"
      },
      "invisible": false,
      "extension": {
        "confirm": {},
        "shape": "",
        "size": "large",
        "defaultValue": "scroll",
        "type": "",
        "dataSource": [
          {
            "label": "不滑动",
            "value": "scroll"
          },
          {
            "label": "滑动效果",
            "value": "fixed"
          }
        ]
      },
      "validateProps": {
        "dataType": "Number",
        "required": false,
        "validate": false
      }
    },
    "1552881039417_1": {
      "type": "Input",
      "dataName": "btitle",
      "label": {
        "description": {
          "icon": "text",
          "desc": "请输入模块大标题"
        },
        "title": "模块标题设置"
      },
      "wrapperStyle": {
        "paddingTop": "20px",
        "borderTop": "1px solid #E1E1E1",
        "marginTop": "20px"
      },
      "style": {
        "width": "auto",
        "height": "auto"
      },
      "invisible": false,
      "extension": {
        "defaultValue": true,
        "useReg": false,
        "placeholder": ""
      },
      "validateProps": {
        "dataType": "",
        "required": false,
        "validate": false
      }
    },
    "1576551642351_1": {
      "type": "Input",
      "dataName": "stitle",
      "label": {
        "description": {
          "icon": "text",
          "desc": "输入模块小标题"
        },
        "title": ""
      },
      "wrapperStyle": {
        "marginTop": "10px"
      },
      "style": {
        "width": "auto",
        "height": "auto"
      },
      "invisible": false,
      "extension": {
        "defaultValue": true,
        "useReg": false,
        "placeholder": ""
      },
      "validateProps": {
        "dataType": "",
        "required": false,
        "validate": false
      }
    },
    "1530760280085_1": {
      "type": "Select",
      "dataName": "mk_tx",
      "label": {
        "description": {
          "icon": "",
          "desc": "模块图片效果"
        },
        "title": ""
      },
      "wrapperStyle": {
        "paddingBottom": "20px",
        "borderBottom": "1px solid #E1E1E1",
        "marginTop": "10px"
      },
      "style": {
        "width": "auto",
        "height": "auto"
      },
      "invisible": false,
      "extension": {
        "defaultValue": "3",
        "placeholder": "",
        "dataSource": [
          {
            "label": "逐渐放大",
            "value": "1"
          },
          {
            "label": "动感滑动",
            "value": "3"
          },
          {
            "label": "无效果",
            "value": "4"
          }
        ]
      },
      "validateProps": {
        "dataType": "",
        "required": false,
        "validate": false
      }
    },
    "1555905786176_1": {
      "type": "Select",
      "dataName": "animat",
      "label": {
        "description": {
          "icon": "",
          "desc": "模块图片效果"
        },
        "title": ""
      },
      "wrapperStyle": {
        "marginTop": "10px"
      },
      "style": {
        "width": "auto",
        "height": "auto"
      },
      "invisible": false,
      "extension": {
        "defaultValue": "11",
        "placeholder": "11",
        "dataSource": [
          {
            "label": "动感光带",
            "value": "6"
          },
          {
            "label": "放大效果",
            "value": "7"
          },
          {
            "label": "放大+线条",
            "value": "8"
          },
          {
            "label": "放大+边框",
            "value": "9"
          },
          {
            "label": "横向翻转",
            "value": "10"
          },
          {
            "label": "十字光带",
            "value": "11"
          },
          {
            "label": "缩小+蒙层+边框",
            "value": "12"
          },
          {
            "label": "动态边框",
            "value": "13"
          },
          {
            "label": "动效蒙层1",
            "value": "14"
          },
          {
            "label": "动效蒙层2",
            "value": "15"
          },
          {
            "label": "动效蒙层3",
            "value": "16"
          },
          {
            "label": "动态圆形",
            "value": "17"
          },
          {
            "label": "上滑效果",
            "value": "1"
          },
          {
            "label": "上下抖动",
            "value": "2"
          },
          {
            "label": "左右抖动",
            "value": "3"
          },
          {
            "label": "旋转抖动",
            "value": "4"
          },
          {
            "label": "弹性缩放",
            "value": "5"
          },
          {
            "label": "无效果",
            "value": "0"
          }
        ]
      },
      "validateProps": {
        "dataType": "",
        "required": false,
        "validate": false
      }
    },
    "1526696631912_2": {
      "type": "SingleImage",
      "dataName": "img0",
      "label": {
        "description": {
          "icon": "picture",
          "desc": "【第1张图片】：宽340，高500"
        },
        "title": "图片设置"
      },
      "wrapperStyle": {
        "marginTop": "10px"
      },
      "style": {
        "width": "auto",
        "height": "auto"
      },
      "invisible": false,
      "extension": {
        "size": 2,
        "saveImageSize": false,
        "api": {
          "uploadUrl": "/v1/image_upload.do"
        },
        "lang": {
          "cropUploadLocale": {
            "image": {
              "cancel": "取消",
              "addPhoto": "上传照片"
            },
            "file": {
              "addPhoto": "上传照片"
            },
            "drag": {
              "dropTips": "可以放手了",
              "dragTips": "直接拖动文件到虚线框内即可上传"
            },
            "crop": {
              "save": "保存并关闭",
              "reset": "重新选择",
              "title": "上传"
            }
          },
          "acceptErrMsg": "不支持该类型的图片，请重新选择",
          "cropSmallError": "您上传的图片超过大小限制，请重新选择图片",
          "cropRecommend": "您上传的图片高度或者宽度太小，请选择尺寸足够的图片",
          "uploadErrMsg": "图片上传失败，请重试"
        }
      },
      "validateProps": {
        "dataType": "",
        "required": false,
        "validate": false
      }
    },
    "1520411453182_1": {
      "type": "Input",
      "dataName": "url0",
      "label": {
        "description": {
          "icon": "link",
          "desc": "请输入链接地址"
        },
        "title": ""
      },
      "wrapperStyle": {
        "marginTop": "10px"
      },
      "style": {
        "width": "auto",
        "height": "auto"
      },
      "invisible": false,
      "extension": {
        "defaultValue": true,
        "useReg": false,
        "placeholder": ""
      },
      "validateProps": {
        "dataType": "",
        "required": false,
        "validate": false
      }
    },
    "1526696631912_7": {
      "type": "SingleImage",
      "dataName": "img1",
      "label": {
        "description": {
          "icon": "picture",
          "desc": "【第2张图片】：宽410，高240"
        },
        "title": ""
      },
      "wrapperStyle": {
        "marginTop": "10px"
      },
      "style": {
        "width": "auto",
        "height": "auto"
      },
      "invisible": false,
      "extension": {
        "size": 2,
        "saveImageSize": false,
        "api": {
          "uploadUrl": "/v1/image_upload.do"
        },
        "lang": {
          "cropUploadLocale": {
            "image": {
              "cancel": "取消",
              "addPhoto": "上传照片"
            },
            "file": {
              "addPhoto": "上传照片"
            },
            "drag": {
              "dropTips": "可以放手了",
              "dragTips": "直接拖动文件到虚线框内即可上传"
            },
            "crop": {
              "save": "保存并关闭",
              "reset": "重新选择",
              "title": "上传"
            }
          },
          "acceptErrMsg": "不支持该类型的图片，请重新选择",
          "cropSmallError": "您上传的图片超过大小限制，请重新选择图片",
          "cropRecommend": "您上传的图片高度或者宽度太小，请选择尺寸足够的图片",
          "uploadErrMsg": "图片上传失败，请重试"
        }
      },
      "validateProps": {
        "dataType": "",
        "required": false,
        "validate": false
      }
    },
    "1520411453182_2": {
      "type": "Input",
      "dataName": "url1",
      "label": {
        "description": {
          "icon": "link",
          "desc": "请输入链接地址"
        },
        "title": ""
      },
      "wrapperStyle": {
        "marginTop": "10px"
      },
      "style": {
        "width": "auto",
        "height": "auto"
      },
      "invisible": false,
      "extension": {
        "defaultValue": true,
        "useReg": false,
        "placeholder": ""
      },
      "validateProps": {
        "dataType": "",
        "required": false,
        "validate": false
      }
    },
    "1526696631912_8": {
      "type": "SingleImage",
      "dataName": "img2",
      "label": {
        "description": {
          "icon": "picture",
          "desc": "【第3张图片】：宽410，高240"
        },
        "title": ""
      },
      "wrapperStyle": {
        "marginTop": "10px"
      },
      "style": {
        "width": "auto",
        "height": "auto"
      },
      "invisible": false,
      "extension": {
        "size": 2,
        "saveImageSize": false,
        "api": {
          "uploadUrl": "/v1/image_upload.do"
        },
        "lang": {
          "cropUploadLocale": {
            "image": {
              "cancel": "取消",
              "addPhoto": "上传照片"
            },
            "file": {
              "addPhoto": "上传照片"
            },
            "drag": {
              "dropTips": "可以放手了",
              "dragTips": "直接拖动文件到虚线框内即可上传"
            },
            "crop": {
              "save": "保存并关闭",
              "reset": "重新选择",
              "title": "上传"
            }
          },
          "acceptErrMsg": "不支持该类型的图片，请重新选择",
          "cropSmallError": "您上传的图片超过大小限制，请重新选择图片",
          "cropRecommend": "您上传的图片高度或者宽度太小，请选择尺寸足够的图片",
          "uploadErrMsg": "图片上传失败，请重试"
        }
      },
      "validateProps": {
        "dataType": "",
        "required": false,
        "validate": false
      }
    },
    "1520411453182_3": {
      "type": "Input",
      "dataName": "url2",
      "label": {
        "description": {
          "icon": "link",
          "desc": "请输入链接地址"
        },
        "title": ""
      },
      "wrapperStyle": {
        "marginTop": "10px"
      },
      "style": {
        "width": "auto",
        "height": "auto"
      },
      "invisible": false,
      "extension": {
        "defaultValue": true,
        "useReg": false,
        "placeholder": ""
      },
      "validateProps": {
        "dataType": "",
        "required": false,
        "validate": false
      }
    },
    "1526696631912_9": {
      "type": "SingleImage",
      "dataName": "img3",
      "label": {
        "description": {
          "icon": "picture",
          "desc": "【第4张图片】：宽410，高240"
        },
        "title": ""
      },
      "wrapperStyle": {
        "marginTop": "10px"
      },
      "style": {
        "width": "auto",
        "height": "auto"
      },
      "invisible": false,
      "extension": {
        "size": 2,
        "saveImageSize": false,
        "api": {
          "uploadUrl": "/v1/image_upload.do"
        },
        "lang": {
          "cropUploadLocale": {
            "image": {
              "cancel": "取消",
              "addPhoto": "上传照片"
            },
            "file": {
              "addPhoto": "上传照片"
            },
            "drag": {
              "dropTips": "可以放手了",
              "dragTips": "直接拖动文件到虚线框内即可上传"
            },
            "crop": {
              "save": "保存并关闭",
              "reset": "重新选择",
              "title": "上传"
            }
          },
          "acceptErrMsg": "不支持该类型的图片，请重新选择",
          "cropSmallError": "您上传的图片超过大小限制，请重新选择图片",
          "cropRecommend": "您上传的图片高度或者宽度太小，请选择尺寸足够的图片",
          "uploadErrMsg": "图片上传失败，请重试"
        }
      },
      "validateProps": {
        "dataType": "",
        "required": false,
        "validate": false
      }
    },
    "1520411453182_4": {
      "type": "Input",
      "dataName": "url3",
      "label": {
        "description": {
          "icon": "link",
          "desc": "请输入链接地址"
        },
        "title": ""
      },
      "wrapperStyle": {
        "marginTop": "10px"
      },
      "style": {
        "width": "auto",
        "height": "auto"
      },
      "invisible": false,
      "extension": {
        "defaultValue": true,
        "useReg": false,
        "placeholder": ""
      },
      "validateProps": {
        "dataType": "",
        "required": false,
        "validate": false
      }
    },
    "1578304119641_1": {
      "type": "SingleImage",
      "dataName": "img4",
      "label": {
        "description": {
          "icon": "picture",
          "desc": "【第5张图片】：宽410，高240"
        },
        "title": ""
      },
      "wrapperStyle": {},
      "style": {
        "width": "auto",
        "height": "auto"
      },
      "invisible": false,
      "extension": {
        "size": 2,
        "saveImageSize": false,
        "width": 0,
        "api": {
          "uploadUrl": "/v1/image_upload.do"
        },
        "lang": {
          "cropUploadLocale": {
            "image": {
              "cancel": "取消",
              "addPhoto": "上传照片"
            },
            "file": {
              "addPhoto": "上传照片"
            },
            "drag": {
              "dropTips": "可以放手了",
              "dragTips": "直接拖动文件到虚线框内即可上传"
            },
            "crop": {
              "save": "保存并关闭",
              "reset": "重新选择",
              "title": "上传"
            }
          },
          "acceptErrMsg": "不支持该类型的图片，请重新选择",
          "cropSmallError": "您上传的图片超过大小限制，请重新选择图片",
          "cropRecommend": "您上传的图片高度或者宽度太小，请选择尺寸足够的图片",
          "uploadErrMsg": "图片上传失败，请重试"
        },
        "height": 0
      },
      "validateProps": {
        "dataType": "",
        "required": false,
        "validate": false
      }
    },
    "1578304119641_2": {
      "type": "Input",
      "dataName": "url4",
      "label": {
        "description": {
          "icon": "link",
          "desc": "请输入链接地址"
        },
        "title": ""
      },
      "wrapperStyle": {
        "marginTop": "10px"
      },
      "style": {
        "width": "auto",
        "height": "auto"
      },
      "invisible": false,
      "extension": {
        "defaultValue": true,
        "useReg": false,
        "placeholder": ""
      },
      "validateProps": {
        "dataType": "",
        "required": false,
        "validate": false
      }
    },
    "1529042159340_1": {
      "type": "Radio",
      "dataName": "mk_style",
      "label": {
        "description": {
          "icon": "",
          "desc": ""
        },
        "title": "自定义模块样式"
      },
      "wrapperStyle": {
        "paddingTop": "20px",
        "borderTop": "1px solid #E1E1E1",
        "marginTop": "20px"
      },
      "style": {
        "width": "auto",
        "height": "auto"
      },
      "invisible": false,
      "extension": {
        "confirm": {},
        "shape": "",
        "size": "large",
        "defaultValue": "2",
        "type": "",
        "dataSource": [
          {
            "label": "收起设置",
            "value": "2"
          },
          {
            "label": "展开设置",
            "value": "1"
          }
        ]
      },
      "validateProps": {
        "dataType": "Number",
        "required": false,
        "validate": false
      }
    },
    "1529738846332_1": {
      "type": "Input",
      "dataName": "paddingTop",
      "label": {
        "description": {
          "icon": "",
          "desc": "模块上间距，填写数字，如20"
        },
        "title": ""
      },
      "wrapperStyle": {
        "marginTop": "10px"
      },
      "style": {
        "width": "auto",
        "height": "auto"
      },
      "invisible": false,
      "extension": {
        "defaultValue": true,
        "useReg": false,
        "placeholder": ""
      },
      "validateProps": {
        "dataType": "Number",
        "required": false,
        "validate": false
      }
    },
    "1524466621760_3": {
      "type": "Input",
      "dataName": "paddingBottom",
      "label": {
        "description": {
          "icon": "",
          "desc": "模块下间距，填写数字，如20"
        },
        "title": ""
      },
      "wrapperStyle": {
        "marginTop": "10px"
      },
      "style": {
        "width": "auto",
        "height": "auto"
      },
      "invisible": false,
      "extension": {
        "defaultValue": true,
        "useReg": false,
        "placeholder": ""
      },
      "validateProps": {
        "dataType": "Number",
        "required": false,
        "validate": false
      }
    },
    "1521862780583_1": {
      "type": "Input",
      "dataName": "mk_bg",
      "label": {
        "description": {
          "icon": "",
          "desc": "模块背景颜色，如#ffffff"
        },
        "title": ""
      },
      "wrapperStyle": {
        "marginTop": "10px"
      },
      "style": {
        "width": "auto",
        "height": "auto"
      },
      "invisible": false,
      "extension": {
        "defaultValue": true,
        "useReg": false,
        "placeholder": ""
      },
      "validateProps": {
        "dataType": "",
        "required": false,
        "validate": false
      }
    },
    "1552881208077_1": {
      "type": "Radio",
      "dataName": "tit_style",
      "label": {
        "description": {
          "icon": "",
          "desc": "自定义模块文字标题样式"
        },
        "title": ""
      },
      "wrapperStyle": {
        "marginTop": "10px"
      },
      "style": {
        "width": "auto",
        "height": "auto"
      },
      "invisible": false,
      "extension": {
        "confirm": {},
        "shape": "",
        "size": "large",
        "defaultValue": "1",
        "type": "",
        "dataSource": [
          {
            "label": "收起设置",
            "value": "1"
          },
          {
            "label": "展开设置",
            "value": "2"
          }
        ]
      },
      "validateProps": {
        "dataType": "Number",
        "required": false,
        "validate": false
      }
    },
    "1552881208077_2": {
      "type": "Select",
      "dataName": "mk_titf",
      "label": {
        "description": {
          "icon": "",
          "desc": "选择模块大标题的字体"
        },
        "title": ""
      },
      "wrapperStyle": {
        "marginTop": "10px"
      },
      "style": {
        "width": "auto",
        "height": "auto"
      },
      "invisible": false,
      "extension": {
        "defaultValue": "Arial",
        "placeholder": "Arial",
        "dataSource": [
          {
            "label": "Arial",
            "value": "Arial"
          },
          {
            "label": "Roboto",
            "value": "Roboto"
          },
          {
            "label": "Helvetica",
            "value": "Helvetica"
          },
          {
            "label": "Neue",
            "value": "Neue"
          },
          {
            "label": "Tahoma",
            "value": "Tahoma"
          },
          {
            "label": "PingFang SC",
            "value": "PingFang SC"
          },
          {
            "label": "Microsoft YaHei",
            "value": "Microsoft YaHei"
          },
          {
            "label": "Century",
            "value": "Century"
          }
        ]
      },
      "validateProps": {
        "dataType": "",
        "required": false,
        "validate": false
      }
    },
    "1552881208077_3": {
      "type": "Input",
      "dataName": "mk_tits",
      "label": {
        "description": {
          "icon": "",
          "desc": "模块大标题文字大小，输入数字"
        },
        "title": ""
      },
      "wrapperStyle": {
        "marginTop": "10px"
      },
      "style": {
        "width": "auto",
        "height": "auto"
      },
      "invisible": false,
      "extension": {
        "defaultValue": true,
        "useReg": false,
        "placeholder": "48"
      },
      "validateProps": {
        "dataType": "",
        "required": false,
        "validate": false
      }
    },
    "1552881208077_4": {
      "type": "Input",
      "dataName": "mk_titc",
      "label": {
        "description": {
          "icon": "",
          "desc": "模块大标题颜色值，如#ffffff"
        },
        "title": ""
      },
      "wrapperStyle": {
        "marginTop": "10px"
      },
      "style": {
        "width": "auto",
        "height": "auto"
      },
      "invisible": false,
      "extension": {
        "defaultValue": true,
        "useReg": false,
        "placeholder": ""
      },
      "validateProps": {
        "dataType": "",
        "required": false,
        "validate": false
      }
    },
    "1576551948330_1": {
      "type": "Input",
      "dataName": "mk_titc2",
      "label": {
        "description": {
          "icon": "",
          "desc": "模块小标题颜色值 ，如#ffffff"
        },
        "title": ""
      },
      "wrapperStyle": {
        "marginTop": "10px"
      },
      "style": {
        "width": "auto",
        "height": "auto"
      },
      "invisible": false,
      "extension": {
        "defaultValue": true,
        "useReg": false,
        "placeholder": ""
      },
      "validateProps": {
        "dataType": "",
        "required": false,
        "validate": false
      }
    },
    "1529720478633_1": {
      "type": "Checkbox",
      "dataName": "target",
      "label": {
        "description": {
          "icon": "",
          "desc": ""
        },
        "title": "其它设置"
      },
      "wrapperStyle": {
        "paddingTop": "20px",
        "borderTop": "1px solid #E1E1E1",
        "marginTop": "20px"
      },
      "style": {
        "width": "auto",
        "height": "auto"
      },
      "invisible": false,
      "extension": {
        "defaultValue": true,
        "text": "链接新窗口打开"
      },
      "validateProps": {
        "dataType": "",
        "required": false,
        "validate": false
      }
    },
    "1524466621760_1": {
      "type": "Checkbox",
      "dataName": "hideBottom",
      "label": {
        "description": {
          "icon": "",
          "desc": ""
        },
        "title": ""
      },
      "wrapperStyle": {
        "marginTop": "10px"
      },
      "style": {
        "width": "auto",
        "height": "auto"
      },
      "invisible": false,
      "extension": {
        "defaultValue": true,
        "text": "去除模块自带的下间距"
      },
      "validateProps": {
        "dataType": "",
        "required": false,
        "validate": false
      }
    }
  },
  "layout": [
    {
      "id": "1557111804637_1",
      "root": true,
      "children": []
    },
    {
      "id": "1557111804637_2",
      "root": true,
      "children": []
    },
    {
      "id": "1557111804637_4",
      "root": true,
      "children": []
    },
    {
      "id": "1552881039417_1",
      "root": true,
      "children": []
    },
    {
      "id": "1576551642351_1",
      "root": true,
      "children": []
    },
    {
      "id": "1530760280085_1",
      "root": true,
      "children": []
    },
    {
      "id": "1555905786176_1",
      "root": true,
      "children": []
    },
    {
      "id": "1526696631912_2",
      "root": true,
      "children": []
    },
    {
      "id": "1520411453182_1",
      "root": true,
      "children": []
    },
    {
      "id": "1526696631912_7",
      "root": true,
      "children": []
    },
    {
      "id": "1520411453182_2",
      "root": true,
      "children": []
    },
    {
      "id": "1526696631912_8",
      "root": true,
      "children": []
    },
    {
      "id": "1520411453182_3",
      "root": true,
      "children": []
    },
    {
      "id": "1526696631912_9",
      "root": true,
      "children": []
    },
    {
      "id": "1520411453182_4",
      "root": true,
      "children": []
    },
    {
      "id": "1578304119641_1",
      "root": true,
      "children": []
    },
    {
      "id": "1578304119641_2",
      "root": true,
      "children": []
    },
    {
      "id": "1529042159340_1",
      "root": true,
      "children": []
    },
    {
      "id": "1529738846332_1",
      "root": true,
      "children": []
    },
    {
      "id": "1524466621760_3",
      "root": true,
      "children": []
    },
    {
      "id": "1521862780583_1",
      "root": true,
      "children": []
    },
    {
      "id": "1552881208077_1",
      "root": true,
      "children": []
    },
    {
      "id": "1552881208077_2",
      "root": true,
      "children": []
    },
    {
      "id": "1552881208077_3",
      "root": true,
      "children": []
    },
    {
      "id": "1552881208077_4",
      "root": true,
      "children": []
    },
    {
      "id": "1576551948330_1",
      "root": true,
      "children": []
    },
    {
      "id": "1529720478633_1",
      "root": true,
      "children": []
    },
    {
      "id": "1524466621760_1",
      "root": true,
      "children": []
    }
  ],
  "globalData": {},
  "rules": [
    {
      "condition": "${moduleData.mk_style}=='2'",
      "components": {
        "1524466621760_3": {
          "invisible": true
        },
        "1529738846332_1": {
          "invisible": true
        },
        "1558925681343_3": {
          "invisible": true
        },
        "1521862780583_1": {
          "invisible": true
        },
        "1529033416917_2": {
          "invisible": true
        },
        "1558925681343_1": {
          "invisible": true
        },
        "1558925681343_2": {
          "invisible": true
        }
      },
      "desc": "模块样式"
    },
    {
      "condition": "${moduleData.tit_style}=='1'",
      "components": {
        "1552881208077_2": {
          "invisible": true
        },
        "1552881208077_4": {
          "invisible": true
        },
        "1552881208077_3": {
          "invisible": true
        },
        "1552881208077_5": {
          "invisible": true
        },
        "1576551948330_1": {
          "invisible": true
        }
      },
      "desc": "模块文字标题样式"
    },
    {
      "condition": "${moduleData.mk_bgDis}=='2'",
      "components": {
        "1557111804637_2": {
          "invisible": true
        },
        "1557111804637_4": {
          "invisible": true
        }
      },
      "desc": "模块背景"
    }
  ],
  "moduleData": {
    "images": {},
    "mk_bgDis": "2",
    "mk_w": "1440",
    "bottom": "",
    "mk_titf": "Arial",
    "hideBottom": true,
    "tit_style": "1",
    "kgd_bg": "",
    "target": true,
    "url3": "",
    "mk_style": "2",
    "url4": "",
    "mk_bgXg": "scroll",
    "url1": "",
    "mk_bg": "",
    "top": "",
    "load": true,
    "url2": "",
    "url0": "",
    "mk_tx": "3"
  }
}